{"version": "0.1.7", "img_width": 1078, "img_height": 1600, "blocks": [{"box": [929, 121, 998, 384], "vertical": true, "font_size": 24, "lines_coords": [[[967.0, 125.0], [988.0, 125.0], [988.0, 312.0], [967.0, 312.0]], [[929.0, 121.0], [956.0, 121.0], [957.0, 384.0], [931.0, 384.0]]], "lines": ["ごめんね長谷くん", "こわい思いさせちゃって"]}, {"box": [729, 32, 879, 94], "vertical": false, "font_size": 38, "lines_coords": [[[731.0, 54.0], [871.0, 48.0], [873.0, 85.0], [732.0, 92.0]]], "lines": ["前回も"]}, {"box": [596, 193, 669, 404], "vertical": true, "font_size": 24, "lines_coords": [[[629.0, 234.0], [656.0, 234.0], [656.0, 401.0], [629.0, 401.0]], [[596.0, 237.0], [618.0, 237.0], [618.0, 379.0], [596.0, 379.0]]], "lines": ["藤宮さんは全然", "悪くないよ！"]}, {"box": [410, 118, 524, 398], "vertical": true, "font_size": 24, "lines_coords": [[[493.0, 120.0], [520.0, 120.0], [520.0, 315.0], [493.0, 315.0]], [[467.0, 118.0], [493.0, 118.0], [492.0, 398.0], [465.0, 398.0]], [[443.0, 121.0], [465.0, 121.0], [465.0, 376.0], [443.0, 376.0]], [[410.0, 120.0], [432.0, 120.0], [432.0, 268.0], [410.0, 268.0]]], "lines": ["後向きに考えてると", "うまくいくはずだったことも", "うまくいかないってことも", "あると思うんだ"]}, {"box": [245, 47, 395, 93], "vertical": false, "font_size": 44, "lines_coords": [[[248.0, 48.0], [376.0, 48.0], [376.0, 92.0], [248.0, 92.0]]], "lines": ["きっと"]}, {"box": [873, 492, 983, 701], "vertical": true, "font_size": 22, "lines_coords": [[[959.0, 492.0], [981.0, 492.0], [981.0, 639.0], [959.0, 639.0]], [[928.0, 492.0], [949.0, 492.0], [949.0, 679.0], [928.0, 679.0]], [[898.0, 492.0], [920.0, 492.0], [920.0, 701.0], [898.0, 701.0]], [[873.0, 492.0], [895.0, 492.0], [895.0, 579.0], [873.0, 579.0]]], "lines": ["でもあれだよね", "こう考えてたら日記", "うまくいきそうな気が", "するよね"]}, {"box": [648, 520, 668, 540], "vertical": false, "font_size": 20, "lines_coords": [[[648.0, 520.0], [668.0, 520.0], [668.0, 540.0], [648.0, 540.0]]], "lines": ["あ"]}, {"box": [613, 546, 637, 614], "vertical": true, "font_size": 24, "lines_coords": [[[613.0, 546.0], [637.0, 546.0], [637.0, 614.0], [613.0, 614.0]]], "lines": ["うん．．．"]}, {"box": [464, 482, 526, 650], "vertical": true, "font_size": 27, "lines_coords": [[[490.0, 482.0], [518.0, 482.0], [520.0, 628.0], [492.0, 628.0]], [[464.0, 482.0], [490.0, 482.0], [490.0, 650.0], [464.0, 650.0]]], "lines": ["だから大丈夫", "うまくいくよ！"]}, {"box": [106, 540, 190, 790], "vertical": true, "font_size": 26, "lines_coords": [[[157.0, 540.0], [184.0, 540.0], [185.0, 723.0], [159.0, 723.0]], [[132.0, 542.0], [162.0, 542.0], [162.0, 612.0], [132.0, 612.0]], [[106.0, 543.0], [128.0, 543.0], [128.0, 790.0], [106.0, 790.0]]], "lines": ["完全じゃなかったと", "しても", "少しは記憶戻るはずだよ！"]}, {"box": [929, 848, 985, 976], "vertical": true, "font_size": 24, "lines_coords": [[[957.0, 848.0], [985.0, 848.0], [985.0, 956.0], [957.0, 956.0]], [[929.0, 850.0], [951.0, 850.0], [951.0, 976.0], [929.0, 976.0]]], "lines": ["本当に記憶", "戻ると思う？"]}, {"box": [879, 985, 904, 1095], "vertical": true, "font_size": 24, "lines_coords": [[[879.0, 985.0], [901.0, 985.0], [904.0, 1095.0], [882.0, 1095.0]]], "lines": ["少しでも．．．"]}, {"box": [788, 945, 823, 1042], "vertical": true, "font_size": 29, "lines_coords": [[[788.0, 945.0], [817.0, 945.0], [817.0, 1042.0], [788.0, 1042.0]]], "lines": ["思うよ！"]}, {"box": [485, 859, 513, 1003], "vertical": true, "font_size": 27, "lines_coords": [[[485.0, 859.0], [512.0, 859.0], [512.0, 1003.0], [485.0, 1003.0]]], "lines": ["そうだよね．．．"]}, {"box": [132, 934, 167, 1076], "vertical": true, "font_size": 27, "lines_coords": [[[132.0, 934.0], [159.0, 934.0], [159.0, 1076.0], [132.0, 1076.0]]], "lines": ["大丈夫だよね"]}, {"box": [937, 1204, 998, 1431], "vertical": true, "font_size": 24, "lines_coords": [[[971.0, 1204.0], [998.0, 1204.0], [998.0, 1425.0], [971.0, 1425.0]], [[938.0, 1207.0], [960.0, 1207.0], [960.0, 1431.0], [938.0, 1431.0]]], "lines": ["やっぱりこういうのは", "前向きに考えなきゃ！！"]}, {"box": [598, 1226, 631, 1314], "vertical": true, "font_size": 28, "lines_coords": [[[598.0, 1226.0], [626.0, 1226.0], [626.0, 1314.0], [598.0, 1314.0]]], "lines": ["前向き．．．"]}, {"box": [474, 1214, 507, 1284], "vertical": true, "font_size": 30, "lines_coords": [[[474.0, 1215.0], [504.0, 1214.0], [507.0, 1282.0], [478.0, 1284.0]]], "lines": ["うんっ"]}, {"box": [293, 1253, 353, 1420], "vertical": true, "font_size": 25, "lines_coords": [[[321.0, 1253.0], [349.0, 1253.0], [349.0, 1340.0], [321.0, 1340.0]], [[293.0, 1256.0], [315.0, 1256.0], [315.0, 1420.0], [293.0, 1420.0]]], "lines": ["だから俺", "屋上で待ってるね"]}]}