{"version": "0.1.7", "img_width": 830, "img_height": 1200, "blocks": [{"box": [369, 69, 444, 148], "vertical": true, "font_size": 27, "lines_coords": [[[416.0, 69.0], [444.0, 69.0], [444.0, 111.0], [416.0, 111.0]], [[391.0, 69.0], [420.0, 69.0], [420.0, 148.0], [391.0, 148.0]], [[369.0, 70.0], [393.0, 70.0], [393.0, 146.0], [369.0, 146.0]]], "lines": ["わー", "かわいい", "かわいい"]}, {"box": [132, 70, 184, 222], "vertical": true, "font_size": 22, "lines_coords": [[[158.0, 71.0], [184.0, 71.0], [184.0, 133.0], [158.0, 133.0]], [[135.0, 70.0], [157.0, 70.0], [153.0, 222.0], [132.0, 222.0]]], "lines": ["でなー", "とーちゃんがなー"]}, {"box": [53, 97, 100, 268], "vertical": true, "font_size": 22, "lines_coords": [[[80.0, 98.0], [100.0, 98.0], [100.0, 268.0], [80.0, 268.0]], [[55.0, 97.0], [76.0, 97.0], [75.0, 268.0], [53.0, 268.0]]], "lines": ["たいふうだからなー", "おくってきてくれた"]}, {"box": [710, 567, 758, 683], "vertical": true, "font_size": 20, "lines_coords": [[[737.0, 568.0], [758.0, 568.0], [756.0, 683.0], [735.0, 683.0]], [[712.0, 567.0], [732.0, 567.0], [730.0, 683.0], [710.0, 683.0]]], "lines": ["よつばちゃん", "どーしたの？"]}, {"box": [645, 618, 668, 754], "vertical": true, "font_size": 20, "lines_coords": [[[648.0, 618.0], [668.0, 618.0], [665.0, 754.0], [645.0, 754.0]]], "lines": ["それ恵那の服？"]}, {"box": [511, 557, 588, 694], "vertical": true, "font_size": 21, "lines_coords": [[[566.0, 558.0], [586.0, 558.0], [586.0, 677.0], [566.0, 677.0]], [[535.0, 557.0], [561.0, 557.0], [561.0, 631.0], [535.0, 631.0]], [[512.0, 560.0], [528.0, 560.0], [528.0, 693.0], [512.0, 693.0]]], "lines": ["ぴしょびしょで", "来たから", "着替えたのよねー"]}, {"box": [75, 564, 121, 678], "vertical": true, "font_size": 22, "lines_coords": [[[97.0, 564.0], [121.0, 564.0], [121.0, 643.0], [97.0, 643.0]], [[75.0, 564.0], [94.0, 564.0], [94.0, 678.0], [75.0, 678.0]]], "lines": ["ふーかだ", "がっこうは？"]}, {"box": [139, 849, 167, 911], "vertical": true, "font_size": 26, "lines_coords": [[[141.0, 849.0], [167.0, 850.0], [165.0, 911.0], [139.0, 910.0]]], "lines": ["はいよ"]}, {"box": [694, 850, 778, 1005], "vertical": true, "font_size": 21, "lines_coords": [[[753.0, 850.0], [778.0, 850.0], [776.0, 948.0], [751.0, 948.0]], [[725.0, 851.0], [745.0, 851.0], [743.0, 967.0], [723.0, 967.0]], [[694.0, 851.0], [713.0, 851.0], [713.0, 1005.0], [694.0, 1005.0]]], "lines": ["フフーーン", "今日は台風で", "学校休みなのだー"]}, {"box": [405, 914, 425, 936], "vertical": true, "font_size": 24, "lines_coords": [[[405.0, 914.0], [425.0, 914.0], [425.0, 936.0], [405.0, 936.0]]], "lines": ["！"]}, {"box": [372, 870, 430, 1019], "vertical": true, "font_size": 24, "lines_coords": [[[402.0, 870.0], [430.0, 870.0], [430.0, 918.0], [402.0, 918.0]], [[375.0, 870.0], [398.0, 870.0], [396.0, 1019.0], [372.0, 1019.0]]], "lines": ["おー", "たいふうでかー"]}, {"box": [269, 844, 321, 987], "vertical": true, "font_size": 22, "lines_coords": [[[301.0, 844.0], [321.0, 844.0], [321.0, 959.0], [301.0, 959.0]], [[269.0, 846.0], [293.0, 846.0], [293.0, 987.0], [269.0, 987.0]]], "lines": ["よつばちゃん", "柿食べようか柿"]}, {"box": [215, 898, 239, 1032], "vertical": true, "font_size": 22, "lines_coords": [[[218.0, 898.0], [239.0, 898.0], [236.0, 1032.0], [215.0, 1032.0]]], "lines": ["風香用意してよ"]}, {"box": [45, 980, 99, 1067], "vertical": true, "font_size": 26, "lines_coords": [[[73.0, 980.0], [99.0, 980.0], [99.0, 1048.0], [73.0, 1048.0]], [[45.0, 983.0], [70.0, 983.0], [70.0, 1067.0], [45.0, 1067.0]]], "lines": ["かきー", "たべるー"]}]}