{"version": "0.1.7", "img_width": 1074, "img_height": 1600, "blocks": [{"box": [855, 117, 1002, 353], "vertical": true, "font_size": 35, "lines_coords": [[[967.0, 117.0], [1002.0, 117.0], [1002.0, 182.0], [967.0, 182.0]]], "lines": ["ねえ"]}, {"box": [859, 118, 959, 356], "vertical": true, "font_size": 29, "lines_coords": [[[928.0, 118.0], [959.0, 118.0], [959.0, 345.0], [928.0, 345.0]], [[891.0, 120.0], [922.0, 120.0], [922.0, 285.0], [891.0, 285.0]], [[861.0, 120.0], [889.0, 120.0], [887.0, 356.0], [859.0, 356.0]]], "lines": ["私今記憶の中から", "大事なものを", "なくしてしまったの"]}, {"box": [794, 342, 820, 503], "vertical": true, "font_size": 29, "lines_coords": [[[794.0, 342.0], [820.0, 342.0], [820.0, 503.0], [794.0, 503.0]]], "lines": ["それが何かは"]}, {"box": [758, 339, 827, 557], "vertical": true, "font_size": 22, "lines_coords": [[[764.0, 346.0], [786.0, 346.0], [786.0, 551.0], [764.0, 551.0]]], "lines": ["わからないけれど"]}, {"box": [858, 762, 877, 830], "vertical": true, "font_size": 19, "lines_coords": [[[858.0, 762.0], [877.0, 762.0], [877.0, 830.0], [858.0, 830.0]]], "lines": ["．．．．．．"]}, {"box": [160, 300, 268, 539], "vertical": true, "font_size": 28, "lines_coords": [[[237.0, 303.0], [264.0, 303.0], [264.0, 539.0], [237.0, 539.0]], [[195.0, 300.0], [226.0, 300.0], [226.0, 492.0], [195.0, 492.0]], [[161.0, 301.0], [187.0, 301.0], [187.0, 514.0], [161.0, 514.0]]], "lines": ["もしかしてあなたの", "大事なものって", "私のと一緒なの！？"]}, {"box": [745, 835, 766, 936], "vertical": true, "font_size": 17, "lines_coords": [[[745.0, 835.0], [762.0, 835.0], [762.0, 934.0], [745.0, 934.0]]], "lines": ["どうかなあ"]}, {"box": [509, 923, 559, 1044], "vertical": true, "font_size": 22, "lines_coords": [[[537.0, 923.0], [559.0, 923.0], [559.0, 1043.0], [537.0, 1043.0]], [[509.0, 925.0], [531.0, 925.0], [531.0, 1006.0], [509.0, 1006.0]]], "lines": ["もしかすると", "違うかも"]}, {"box": [142, 909, 173, 964], "vertical": true, "font_size": 31, "lines_coords": [[[142.0, 909.0], [173.0, 909.0], [173.0, 964.0], [142.0, 964.0]]], "lines": ["でも"]}, {"box": [537, 1208, 631, 1457], "vertical": true, "font_size": 35, "lines_coords": [[[583.0, 1209.0], [622.0, 1209.0], [622.0, 1396.0], [583.0, 1396.0]], [[539.0, 1210.0], [570.0, 1210.0], [570.0, 1457.0], [539.0, 1457.0]]], "lines": ["俺は一緒だと", "いいなって思うよ"]}]}