{"version": "0.1.7", "img_width": 1472, "img_height": 2145, "blocks": [{"box": [925, 148, 990, 335], "vertical": true, "font_size": 32, "lines_coords": [[[954.0, 148.0], [990.0, 148.0], [990.0, 259.0], [954.0, 259.0]], [[925.0, 150.0], [952.0, 150.0], [952.0, 335.0], [925.0, 335.0]]], "lines": ["こわくは", "なかったけどね"]}, {"box": [885, 808, 927, 848], "vertical": true, "font_size": 39, "lines_coords": [[[885.0, 808.0], [927.0, 808.0], [927.0, 848.0], [885.0, 848.0]]], "lines": ["お"]}, {"box": [705, 682, 793, 816], "vertical": true, "font_size": 39, "lines_coords": [[[755.0, 684.0], [793.0, 684.0], [793.0, 816.0], [755.0, 816.0]], [[705.0, 682.0], [743.0, 682.0], [743.0, 816.0], [705.0, 816.0]]], "lines": ["変わった", "犬がきた"]}]}