{"version": "0.1.6", "img_width": 1443, "img_height": 2048, "blocks": [{"box": [1213, 150, 1307, 422], "vertical": true, "font_size": 25, "lines_coords": [[[1279.0, 152.0], [1305.0, 152.0], [1305.0, 396.0], [1279.0, 396.0]], [[1245.0, 150.0], [1271.0, 150.0], [1271.0, 422.0], [1245.0, 422.0]], [[1215.0, 154.0], [1237.0, 154.0], [1237.0, 288.0], [1215.0, 288.0]]], "lines": ["しじまちゃんも小説", "とか書きたくなったら", "相談してね"]}, {"box": [773, 234, 804, 414], "vertical": true, "font_size": 28, "lines_coords": [[[773.0, 234.0], [801.0, 234.0], [801.0, 414.0], [773.0, 414.0]]], "lines": ["書かないです"]}, {"box": [620, 198, 640, 316], "vertical": true, "font_size": 20, "lines_coords": [[[620.0, 198.0], [640.0, 198.0], [640.0, 316.0], [620.0, 316.0]]], "lines": ["．．．．．．"]}, {"box": [231, 260, 314, 470], "vertical": true, "font_size": 26, "lines_coords": [[[287.0, 260.0], [313.0, 260.0], [313.0, 446.0], [287.0, 446.0]], [[257.0, 262.0], [283.0, 262.0], [283.0, 446.0], [257.0, 446.0]], [[231.0, 264.0], [257.0, 264.0], [257.0, 470.0], [231.0, 470.0]]], "lines": ["．．．よしこちゃんは", "詩を書くなら何に", "ついて書きたいの？"]}, {"box": [1156, 660, 1177, 755], "vertical": true, "font_size": 21, "lines_coords": [[[1156.0, 660.0], [1177.0, 660.0], [1177.0, 755.0], [1156.0, 755.0]]], "lines": ["．．．．．．？"]}, {"box": [887, 698, 910, 803], "vertical": true, "font_size": 23, "lines_coords": [[[887.0, 698.0], [910.0, 698.0], [910.0, 803.0], [887.0, 803.0]]], "lines": ["．．．．．．"]}, {"box": [654, 617, 681, 720], "vertical": true, "font_size": 22, "lines_coords": [[[657.0, 618.0], [679.0, 618.0], [679.0, 720.0], [657.0, 720.0]]], "lines": ["．．．私は．．．"]}, {"box": [141, 870, 172, 960], "vertical": true, "font_size": 30, "lines_coords": [[[141.0, 872.0], [171.0, 872.0], [171.0, 958.0], [141.0, 958.0]]], "lines": ["．．．雨？"]}, {"box": [1239, 1064, 1299, 1336], "vertical": true, "font_size": 26, "lines_coords": [[[1271.0, 1064.0], [1297.0, 1064.0], [1297.0, 1252.0], [1271.0, 1252.0]], [[1239.0, 1066.0], [1265.0, 1066.0], [1265.0, 1336.0], [1239.0, 1336.0]]], "lines": ["あ．．．そういえば", "私も一つ詩を書いたよ"]}, {"box": [783, 1066, 814, 1271], "vertical": true, "font_size": 28, "lines_coords": [[[783.0, 1066.0], [811.0, 1066.0], [813.0, 1268.0], [785.0, 1268.0]]], "lines": ["えっどんな．．．？"]}, {"box": [639, 1074, 673, 1199], "vertical": true, "font_size": 34, "lines_coords": [[[639.0, 1074.0], [673.0, 1074.0], [673.0, 1198.0], [639.0, 1198.0]]], "lines": ["これ．．．"]}, {"box": [765, 1350, 795, 1436], "vertical": true, "font_size": 30, "lines_coords": [[[765.0, 1350.0], [795.0, 1350.0], [795.0, 1436.0], [765.0, 1436.0]]], "lines": ["こんな"]}, {"box": [221, 1253, 287, 1427], "vertical": true, "font_size": 28, "lines_coords": [[[257.0, 1254.0], [285.0, 1254.0], [285.0, 1426.0], [257.0, 1426.0]], [[221.0, 1256.0], [249.0, 1256.0], [249.0, 1398.0], [221.0, 1398.0]]], "lines": ["こんぺいとう", "みたい．．．"]}, {"box": [1249, 1508, 1307, 1676], "vertical": true, "font_size": 27, "lines_coords": [[[1279.0, 1508.0], [1307.0, 1508.0], [1307.0, 1606.0], [1279.0, 1606.0]], [[1249.0, 1510.0], [1275.0, 1510.0], [1275.0, 1676.0], [1249.0, 1676.0]]], "lines": ["モサモサ", "モササウルス．．．"]}, {"box": [865, 1509, 919, 1682], "vertical": true, "font_size": 24, "lines_coords": [[[893.0, 1510.0], [919.0, 1510.0], [919.0, 1682.0], [893.0, 1682.0]], [[865.0, 1510.0], [887.0, 1510.0], [887.0, 1658.0], [865.0, 1658.0]]], "lines": ["これは．．．なんの", "歌なんだろう"]}, {"box": [777, 1726, 829, 1900], "vertical": true, "font_size": 25, "lines_coords": [[[801.0, 1726.0], [829.0, 1726.0], [829.0, 1900.0], [801.0, 1900.0]], [[777.0, 1726.0], [799.0, 1726.0], [799.0, 1814.0], [777.0, 1814.0]]], "lines": ["．．．モササウルスの", "うた．．．？"]}, {"box": [610, 1608, 633, 1698], "vertical": true, "font_size": 23, "lines_coords": [[[610.0, 1608.0], [633.0, 1608.0], [633.0, 1698.0], [610.0, 1698.0]]], "lines": ["．．．．．．"]}, {"box": [117, 1811, 157, 1852], "vertical": false, "font_size": 38, "lines_coords": [[[117.0, 1814.0], [157.0, 1814.0], [157.0, 1852.0], [117.0, 1852.0]]], "lines": ["あ"]}]}