{"version": "0.1.7", "img_width": 1443, "img_height": 2048, "blocks": [{"box": [38, 23, 229, 61], "vertical": false, "font_size": 28, "lines_coords": [[[45.0, 26.0], [221.0, 26.0], [221.0, 56.0], [45.0, 56.0]]], "lines": ["ＲａｗＬａｚｙ．Ｓｉ"]}, {"box": [327, 312, 385, 445], "vertical": true, "font_size": 26, "lines_coords": [[[359.0, 314.0], [381.0, 314.0], [381.0, 444.0], [359.0, 444.0]], [[327.0, 312.0], [357.0, 312.0], [357.0, 392.0], [327.0, 392.0]]], "lines": ["なあそこの", "君たち"]}, {"box": [167, 531, 223, 650], "vertical": true, "font_size": 22, "lines_coords": [[[197.0, 532.0], [219.0, 532.0], [219.0, 650.0], [197.0, 650.0]], [[167.0, 532.0], [189.0, 532.0], [189.0, 650.0], [167.0, 650.0]]], "lines": ["手を貸して", "くれないか"]}, {"box": [127, 878, 193, 984], "vertical": true, "font_size": 37, "lines_coords": [[[157.0, 880.0], [193.0, 880.0], [193.0, 984.0], [157.0, 984.0]], [[127.0, 878.0], [165.0, 878.0], [165.0, 938.0], [127.0, 938.0]]], "lines": ["こっちに", "来て"]}, {"box": [1237, 1284, 1296, 1416], "vertical": true, "font_size": 28, "lines_coords": [[[1267.0, 1284.0], [1295.0, 1284.0], [1295.0, 1414.0], [1267.0, 1414.0]], [[1237.0, 1284.0], [1265.0, 1284.0], [1265.0, 1416.0], [1237.0, 1416.0]]], "lines": ["押し込んで", "ほしいんだ"]}, {"box": [863, 1112, 921, 1210], "vertical": true, "font_size": 30, "lines_coords": [[[891.0, 1112.0], [921.0, 1112.0], [921.0, 1208.0], [891.0, 1208.0]], [[863.0, 1112.0], [893.0, 1112.0], [893.0, 1210.0], [863.0, 1210.0]]], "lines": ["詰まって", "しまって"]}, {"box": [763, 1063, 818, 1220], "vertical": true, "font_size": 28, "lines_coords": [[[763.0, 1066.0], [791.0, 1066.0], [791.0, 1220.0], [763.0, 1220.0]]], "lines": ["こうですか！？"]}, {"box": [1101, 1512, 1189, 1708], "vertical": true, "font_size": 28, "lines_coords": [[[1155.0, 1512.0], [1189.0, 1512.0], [1189.0, 1618.0], [1155.0, 1618.0]], [[1129.0, 1516.0], [1157.0, 1516.0], [1157.0, 1708.0], [1129.0, 1708.0]], [[1101.0, 1518.0], [1123.0, 1518.0], [1123.0, 1660.0], [1101.0, 1660.0]]], "lines": ["それから", "そこのハンドルを", "回してほしい"]}, {"box": [1212, 1984, 1417, 2019], "vertical": false, "font_size": 38, "lines_coords": [[[1212.0, 1981.0], [1417.0, 1981.0], [1417.0, 2022.0], [1212.0, 2022.0]]], "lines": ["ＤＬ－Ｒａｗ．Ｓｅ"]}, {"box": [419, 1796, 447, 1872], "vertical": true, "font_size": 28, "lines_coords": [[[419.0, 1796.0], [447.0, 1796.0], [447.0, 1872.0], [419.0, 1872.0]]], "lines": ["ああ．．．"]}, {"box": [191, 1521, 216, 1663], "vertical": true, "font_size": 22, "lines_coords": [[[191.0, 1522.0], [213.0, 1522.0], [213.0, 1662.0], [191.0, 1662.0]]], "lines": ["すばらしい．．．"]}]}