{"version": "0.1.6", "img_width": 1443, "img_height": 2048, "blocks": [{"box": [777, 230, 813, 417], "vertical": true, "font_size": 34, "lines_coords": [[[777.0, 230.0], [811.0, 230.0], [811.0, 416.0], [777.0, 416.0]]], "lines": ["先生先生ー"]}, {"box": [605, 150, 671, 392], "vertical": true, "font_size": 31, "lines_coords": [[[643.0, 152.0], [671.0, 152.0], [671.0, 378.0], [643.0, 378.0]], [[605.0, 150.0], [639.0, 150.0], [639.0, 392.0], [605.0, 392.0]]], "lines": ["．．．今日はそういう", "天気？なのかな．．．"]}, {"box": [135, 308, 170, 520], "vertical": true, "font_size": 34, "lines_coords": [[[135.0, 308.0], [169.0, 308.0], [169.0, 520.0], [135.0, 520.0]]], "lines": ["．．．あ！そうだ"]}, {"box": [1275, 605, 1297, 731], "vertical": true, "font_size": 22, "lines_coords": [[[1275.0, 608.0], [1297.0, 608.0], [1297.0, 730.0], [1275.0, 730.0]]], "lines": ["どうした？"]}, {"box": [1179, 802, 1267, 988], "vertical": true, "font_size": 23, "lines_coords": [[[1237.0, 804.0], [1259.0, 804.0], [1259.0, 942.0], [1237.0, 942.0]], [[1205.0, 802.0], [1231.0, 802.0], [1231.0, 988.0], [1205.0, 988.0]], [[1179.0, 804.0], [1201.0, 804.0], [1201.0, 898.0], [1179.0, 898.0]]], "lines": ["なんか音符で", "前が見えづらいん", "ですか．．．"]}, {"box": [781, 602, 837, 776], "vertical": true, "font_size": 24, "lines_coords": [[[813.0, 606.0], [835.0, 606.0], [835.0, 726.0], [813.0, 726.0]], [[781.0, 602.0], [807.0, 602.0], [807.0, 776.0], [781.0, 776.0]]], "lines": ["おい誰だ？", "音符出してるの"]}, {"box": [637, 619, 671, 742], "vertical": true, "font_size": 26, "lines_coords": [[[645.0, 668.0], [671.0, 672.0], [663.0, 742.0], [637.0, 738.0]]], "lines": ["何？"]}, {"box": [429, 610, 471, 672], "vertical": true, "font_size": 42, "lines_coords": [[[429.0, 610.0], [471.0, 610.0], [471.0, 672.0], [429.0, 672.0]]], "lines": ["おっ"]}, {"box": [129, 854, 171, 958], "vertical": true, "font_size": 42, "lines_coords": [[[129.0, 854.0], [171.0, 854.0], [171.0, 958.0], [129.0, 958.0]]], "lines": ["出た．．．"]}, {"box": [1171, 1046, 1229, 1262], "vertical": true, "font_size": 26, "lines_coords": [[[1203.0, 1048.0], [1229.0, 1048.0], [1229.0, 1206.0], [1203.0, 1206.0]], [[1171.0, 1046.0], [1197.0, 1046.0], [1197.0, 1262.0], [1171.0, 1262.0]]], "lines": ["．．．おいあやか", "頭から音符出てるぞ"]}, {"box": [795, 1370, 841, 1450], "vertical": true, "font_size": 46, "lines_coords": [[[795.0, 1370.0], [841.0, 1370.0], [841.0, 1450.0], [795.0, 1450.0]]], "lines": ["え？"]}, {"box": [597, 1076, 671, 1320], "vertical": true, "font_size": 34, "lines_coords": [[[637.0, 1076.0], [671.0, 1076.0], [669.0, 1320.0], [635.0, 1320.0]], [[597.0, 1078.0], [631.0, 1078.0], [631.0, 1208.0], [597.0, 1208.0]]], "lines": ["ほらひらめいた", "時の電球"]}, {"box": [519, 1069, 547, 1182], "vertical": true, "font_size": 28, "lines_coords": [[[519.0, 1070.0], [547.0, 1070.0], [547.0, 1182.0], [519.0, 1182.0]]], "lines": ["本当だ．．．"]}, {"box": [185, 1058, 244, 1270], "vertical": true, "font_size": 26, "lines_coords": [[[217.0, 1058.0], [243.0, 1058.0], [243.0, 1242.0], [217.0, 1242.0]], [[185.0, 1060.0], [211.0, 1060.0], [211.0, 1270.0], [185.0, 1270.0]]], "lines": ["しめじちゃんも", "ひらめいてみてよ"]}, {"box": [248, 1277, 292, 1402], "vertical": true, "font_size": 44, "lines_coords": [[[248.0, 1277.0], [292.0, 1277.0], [292.0, 1402.0], [248.0, 1402.0]]], "lines": ["ついでも大丈夫ほいよ"]}, {"box": [129, 1292, 187, 1439], "vertical": true, "font_size": 25, "lines_coords": [[[159.0, 1294.0], [183.0, 1292.0], [187.0, 1366.0], [163.0, 1368.0]], [[133.0, 1292.0], [159.0, 1292.0], [155.0, 1438.0], [129.0, 1438.0]]], "lines": ["え．．．．．", "できるかな．．"]}, {"box": [1315, 1660, 1373, 1840], "vertical": true, "font_size": 27, "lines_coords": [[[1347.0, 1662.0], [1373.0, 1662.0], [1373.0, 1840.0], [1347.0, 1840.0]], [[1315.0, 1660.0], [1343.0, 1660.0], [1343.0, 1766.0], [1315.0, 1766.0]]], "lines": ["みたいなことが", "あって．．．"]}, {"box": [619, 1556, 673, 1614], "vertical": true, "font_size": 54, "lines_coords": [[[619.0, 1556.0], [673.0, 1556.0], [673.0, 1614.0], [619.0, 1614.0]]], "lines": ["！！"]}, {"box": [159, 1511, 192, 1720], "vertical": true, "font_size": 28, "lines_coords": [[[159.0, 1514.0], [187.0, 1514.0], [187.0, 1720.0], [159.0, 1720.0]]], "lines": ["なんでヒラメ？"]}]}