{"version": "0.1.7", "img_width": 1092, "img_height": 1600, "blocks": [{"box": [921, 790, 1040, 942], "vertical": true, "font_size": 38, "lines_coords": [[[996.0, 790.0], [1040.0, 790.0], [1040.0, 862.0], [996.0, 862.0]], [[965.0, 795.0], [993.0, 795.0], [993.0, 942.0], [965.0, 942.0]], [[921.0, 790.0], [962.0, 790.0], [962.0, 887.0], [921.0, 887.0]]], "lines": ["あ！", "とーちゃん", "きた！"]}, {"box": [487, 784, 562, 958], "vertical": true, "font_size": 34, "lines_coords": [[[520.0, 784.0], [562.0, 784.0], [562.0, 848.0], [520.0, 848.0]], [[488.0, 789.0], [515.0, 789.0], [513.0, 957.0], [487.0, 957.0]]], "lines": ["あーとう", "お父さん来たの"]}, {"box": [312, 782, 378, 934], "vertical": true, "font_size": 32, "lines_coords": [[[343.0, 782.0], [378.0, 782.0], [378.0, 865.0], [343.0, 865.0]], [[315.0, 784.0], [343.0, 784.0], [340.0, 934.0], [312.0, 934.0]]], "lines": ["どうも", "スミマセン！"]}, {"box": [118, 954, 188, 1175], "vertical": true, "font_size": 25, "lines_coords": [[[149.0, 954.0], [176.0, 954.0], [176.0, 1056.0], [149.0, 1056.0]], [[120.0, 956.0], [143.0, 956.0], [142.0, 1145.0], [118.0, 1145.0]]], "lines": ["ご迷惑を", "おかけしましてー"]}]}