{"version": "0.1.7", "img_width": 1093, "img_height": 1600, "blocks": [{"box": [943, 73, 1033, 307], "vertical": true, "font_size": 24, "lines_coords": [[[1007.0, 73.0], [1033.0, 73.0], [1033.0, 242.0], [1007.0, 242.0]], [[974.0, 75.0], [1000.0, 75.0], [1000.0, 193.0], [974.0, 193.0]], [[947.0, 73.0], [969.0, 73.0], [964.0, 307.0], [943.0, 307.0]]], "lines": ["ねぇここの栗って", "勝手に取って", "持って帰ってもいいもの？"]}, {"box": [866, 107, 888, 262], "vertical": true, "font_size": 24, "lines_coords": [[[866.0, 107.0], [888.0, 107.0], [888.0, 262.0], [866.0, 262.0]]], "lines": ["怒られないの？"]}, {"box": [367, 355, 390, 419], "vertical": true, "font_size": 23, "lines_coords": [[[367.0, 355.0], [390.0, 355.0], [390.0, 419.0], [367.0, 419.0]]], "lines": ["．．．．．"]}, {"box": [127, 395, 149, 458], "vertical": true, "font_size": 22, "lines_coords": [[[127.0, 395.0], [149.0, 395.0], [149.0, 458.0], [127.0, 458.0]]], "lines": ["．．．．．"]}, {"box": [958, 723, 1015, 926], "vertical": true, "font_size": 42, "lines_coords": [[[958.0, 723.0], [1000.0, 723.0], [1000.0, 926.0], [958.0, 926.0]]], "lines": ["怒られたら"]}, {"box": [238, 745, 279, 948], "vertical": true, "font_size": 38, "lines_coords": [[[242.0, 745.0], [279.0, 745.0], [276.0, 948.0], [238.0, 948.0]]], "lines": ["あやまろう"]}, {"box": [961, 1221, 1027, 1362], "vertical": true, "font_size": 23, "lines_coords": [[[961.0, 1228.0], [983.0, 1228.0], [983.0, 1362.0], [961.0, 1362.0]], [[1007.0, 1221.0], [1027.0, 1242.0], [1008.0, 1262.0], [988.0, 1242.0]]], "lines": ["それで行こう", "．．．"]}, {"box": [552, 1245, 646, 1397], "vertical": true, "font_size": 29, "lines_coords": [[[619.0, 1246.0], [646.0, 1246.0], [643.0, 1396.0], [616.0, 1396.0]], [[587.0, 1246.0], [613.0, 1246.0], [613.0, 1396.0], [587.0, 1396.0]], [[552.0, 1245.0], [585.0, 1245.0], [585.0, 1326.0], [552.0, 1326.0]]], "lines": ["おこられても", "うそついたら", "だめ！"]}, {"box": [123, 1307, 191, 1443], "vertical": true, "font_size": 27, "lines_coords": [[[162.0, 1309.0], [190.0, 1309.0], [190.0, 1443.0], [162.0, 1443.0]], [[123.0, 1307.0], [149.0, 1307.0], [149.0, 1407.0], [123.0, 1407.0]]], "lines": ["おいいこと", "言うねぇ"]}]}