{"version": "0.1.7", "img_width": 1100, "img_height": 1600, "blocks": [{"box": [651, 79, 774, 230], "vertical": true, "font_size": 25, "lines_coords": [[[746.0, 79.0], [773.0, 79.0], [773.0, 204.0], [746.0, 204.0]], [[714.0, 79.0], [740.0, 79.0], [740.0, 226.0], [714.0, 226.0]], [[681.0, 79.0], [707.0, 79.0], [707.0, 178.0], [681.0, 178.0]], [[651.0, 79.0], [673.0, 79.0], [673.0, 225.0], [651.0, 225.0]]], "lines": ["ジャンボも", "とりたいけど", "おみせが", "とおいから．．．"]}, {"box": [603, 86, 773, 462], "vertical": true, "font_size": 26, "lines_coords": [[[664.0, 298.0], [690.0, 298.0], [690.0, 448.0], [664.0, 448.0]], [[632.0, 301.0], [659.0, 301.0], [659.0, 448.0], [632.0, 448.0]]], "lines": ["とーちゃんに", "つれていって"]}, {"box": [487, 68, 544, 218], "vertical": true, "font_size": 24, "lines_coords": [[[517.0, 68.0], [543.0, 68.0], [540.0, 218.0], [514.0, 218.0]], [[487.0, 70.0], [509.0, 70.0], [509.0, 167.0], [487.0, 167.0]]], "lines": ["かーちゃんも", "あさぎも"]}, {"box": [600, 298, 691, 471], "vertical": true, "font_size": 24, "lines_coords": [[[601.0, 298.0], [625.0, 298.0], [623.0, 471.0], [600.0, 471.0]]], "lines": ["もらわないと．．"]}, {"box": [257, 65, 315, 165], "vertical": true, "font_size": 26, "lines_coords": [[[289.0, 67.0], [315.0, 67.0], [315.0, 165.0], [289.0, 165.0]], [[257.0, 65.0], [285.0, 65.0], [285.0, 143.0], [257.0, 143.0]]], "lines": ["ふーかも", "えなも"]}, {"box": [156, 132, 212, 254], "vertical": true, "font_size": 26, "lines_coords": [[[185.0, 132.0], [212.0, 132.0], [212.0, 232.0], [185.0, 232.0]], [[156.0, 134.0], [178.0, 134.0], [178.0, 254.0], [156.0, 254.0]]], "lines": ["みうらも", "ダンボーも"]}, {"box": [165, 335, 257, 460], "vertical": true, "font_size": 26, "lines_coords": [[[229.0, 335.0], [257.0, 335.0], [257.0, 415.0], [229.0, 415.0]], [[198.0, 335.0], [225.0, 335.0], [225.0, 460.0], [198.0, 460.0]], [[168.0, 335.0], [195.0, 335.0], [192.0, 460.0], [165.0, 460.0]]], "lines": ["みんな", "とらないと", "いけない．．．"]}, {"box": [924, 620, 954, 739], "vertical": true, "font_size": 28, "lines_coords": [[[925.0, 620.0], [953.0, 620.0], [953.0, 739.0], [925.0, 739.0]]], "lines": ["こいつは"]}, {"box": [282, 604, 358, 843], "vertical": true, "font_size": 32, "lines_coords": [[[325.0, 609.0], [357.0, 609.0], [357.0, 759.0], [325.0, 759.0]], [[287.0, 604.0], [320.0, 604.0], [315.0, 843.0], [282.0, 843.0]]], "lines": ["いそがしく", "なってきやがった"]}]}