{"version": "0.1.7", "img_width": 975, "img_height": 1400, "blocks": [{"box": [808, 865, 858, 1050], "vertical": true, "font_size": 50, "lines_coords": [[[808.0, 865.0], [858.0, 865.0], [858.0, 929.0], [808.0, 929.0]]], "lines": ["あー"]}, {"box": [496, 875, 545, 1061], "vertical": true, "font_size": 49, "lines_coords": [[[496.0, 875.0], [545.0, 875.0], [545.0, 944.0], [496.0, 944.0]]], "lines": ["あー"]}, {"box": [105, 877, 231, 1081], "vertical": true, "font_size": 62, "lines_coords": [[[172.0, 877.0], [231.0, 879.0], [225.0, 1081.0], [166.0, 1080.0]], [[110.0, 877.0], [175.0, 879.0], [169.0, 1077.0], [105.0, 1075.0]]], "lines": ["もどれ！！", "よつば！！"]}]}