{"version": "0.1.7", "img_width": 1078, "img_height": 1600, "blocks": [{"box": [139, 68, 320, 90], "vertical": false, "font_size": 22, "lines_coords": [[[139.0, 68.0], [320.0, 68.0], [320.0, 90.0], [139.0, 90.0]]], "lines": ["週間フレンズ"]}, {"box": [328, 777, 358, 902], "vertical": true, "font_size": 21, "lines_coords": [[[328.0, 778.0], [349.0, 778.0], [349.0, 901.0], [328.0, 901.0]]], "lines": ["山岸さん．．．？"]}, {"box": [241, 1173, 311, 1315], "vertical": true, "font_size": 25, "lines_coords": [[[273.0, 1173.0], [301.0, 1173.0], [298.0, 1303.0], [270.0, 1303.0]], [[242.0, 1176.0], [264.0, 1176.0], [264.0, 1292.0], [242.0, 1292.0]]], "lines": ["やっぱい授業", "遅刻だ．．．！！"]}]}