{"version": "0.1.7", "img_width": 844, "img_height": 1200, "blocks": [{"box": [712, 120, 732, 200], "vertical": true, "font_size": 20, "lines_coords": [[[712.0, 120.0], [732.0, 120.0], [732.0, 200.0], [712.0, 200.0]]], "lines": ["それで．．．？"]}, {"box": [497, 129, 535, 269], "vertical": true, "font_size": 16, "lines_coords": [[[515.0, 130.0], [532.0, 130.0], [532.0, 268.0], [515.0, 268.0]], [[497.0, 130.0], [512.0, 130.0], [512.0, 269.0], [497.0, 269.0]]], "lines": ["断言できるものでは", "ないらしいんだけど"]}, {"box": [342, 141, 427, 343], "vertical": true, "font_size": 16, "lines_coords": [[[407.0, 142.0], [424.0, 142.0], [424.0, 229.0], [407.0, 229.0]], [[385.0, 141.0], [402.0, 141.0], [399.0, 315.0], [383.0, 315.0]], [[363.0, 141.0], [379.0, 141.0], [379.0, 329.0], [363.0, 329.0]], [[342.0, 141.0], [358.0, 141.0], [358.0, 343.0], [342.0, 343.0]]], "lines": ["友達の記憶を", "保持できないということは", "自分自身が友達という存在を", "拒絶している可能性が高いって"]}, {"box": [710, 547, 736, 600], "vertical": true, "font_size": 22, "lines_coords": [[[710.0, 547.0], [732.0, 547.0], [732.0, 600.0], [710.0, 600.0]]], "lines": ["拒絶．．．"]}, {"box": [98, 534, 180, 691], "vertical": true, "font_size": 18, "lines_coords": [[[154.0, 534.0], [180.0, 534.0], [180.0, 573.0], [154.0, 573.0]], [[135.0, 537.0], [152.0, 537.0], [152.0, 691.0], [135.0, 691.0]], [[117.0, 537.0], [133.0, 537.0], [133.0, 676.0], [117.0, 676.0]], [[98.0, 537.0], [113.0, 537.0], [113.0, 630.0], [98.0, 630.0]]], "lines": ["でも", "なんで拒絶するように", "なってしまったかは", "わからないし"]}, {"box": [686, 840, 738, 1007], "vertical": true, "font_size": 22, "lines_coords": [[[711.0, 840.0], [734.0, 840.0], [734.0, 992.0], [711.0, 992.0]], [[686.0, 841.0], [706.0, 841.0], [706.0, 1007.0], [686.0, 1007.0]]], "lines": ["一から友達を作って", "乗り越えようとしても"]}, {"box": [426, 864, 524, 1086], "vertical": true, "font_size": 20, "lines_coords": [[[497.0, 864.0], [520.0, 864.0], [518.0, 1086.0], [494.0, 1086.0]], [[472.0, 866.0], [492.0, 866.0], [492.0, 1004.0], [472.0, 1004.0]], [[446.0, 867.0], [466.0, 867.0], [466.0, 1050.0], [446.0, 1050.0]], [[426.0, 868.0], [443.0, 868.0], [443.0, 967.0], [426.0, 967.0]]], "lines": ["一週間で記憶が消えてしまう", "悲しさが強すぎて", "もはやハ方塞がりだった", "みたいだけど"]}]}