{"version": "0.1.7", "img_width": 844, "img_height": 1200, "blocks": [{"box": [104, 51, 287, 77], "vertical": false, "font_size": 24, "lines_coords": [[[104.0, 51.0], [287.0, 53.0], [287.0, 77.0], [104.0, 75.0]]], "lines": ["一週間フレンズ。口"]}, {"box": [713, 525, 739, 628], "vertical": true, "font_size": 20, "lines_coords": [[[713.0, 525.0], [733.0, 525.0], [733.0, 628.0], [713.0, 628.0]]], "lines": ["よく頑張った"]}, {"box": [132, 931, 153, 1040], "vertical": true, "font_size": 16, "lines_coords": [[[133.0, 931.0], [150.0, 931.0], [148.0, 1040.0], [132.0, 1040.0]]], "lines": ["褒められ．．．た？"]}]}