{"version": "0.1.7", "img_width": 835, "img_height": 1200, "blocks": [{"box": [738, 55, 797, 219], "vertical": true, "font_size": 16, "lines_coords": [[[778.0, 57.0], [795.0, 57.0], [795.0, 132.0], [778.0, 132.0]], [[761.0, 56.0], [777.0, 56.0], [776.0, 219.0], [760.0, 219.0]], [[742.0, 55.0], [758.0, 55.0], [755.0, 146.0], [738.0, 146.0]]], "lines": ["ばーちゃん", "よつばいいこにしてたか", "どうかきいて"]}, {"box": [575, 126, 598, 207], "vertical": true, "font_size": 16, "lines_coords": [[[576.0, 126.0], [592.0, 126.0], [592.0, 207.0], [576.0, 207.0]]], "lines": ["え？何それ"]}, {"box": [459, 48, 509, 223], "vertical": true, "font_size": 50, "lines_coords": [[[459.0, 49.0], [509.0, 49.0], [509.0, 223.0], [459.0, 223.0]]], "lines": ["してた！！"]}, {"box": [567, 295, 608, 427], "vertical": true, "font_size": 16, "lines_coords": [[[589.0, 295.0], [605.0, 295.0], [605.0, 426.0], [589.0, 426.0]], [[567.0, 295.0], [583.0, 295.0], [583.0, 396.0], [567.0, 396.0]]], "lines": ["よつばはいい子に", "してたかい？"]}, {"box": [604, 876, 644, 1007], "vertical": true, "font_size": 18, "lines_coords": [[[624.0, 876.0], [644.0, 876.0], [644.0, 959.0], [624.0, 959.0]], [[604.0, 877.0], [620.0, 877.0], [620.0, 1007.0], [604.0, 1007.0]]], "lines": ["．．．いいこに", "してたけどなー．．．"]}]}