{"version": "0.1.7", "img_width": 830, "img_height": 1200, "blocks": [{"box": [609, 888, 631, 909], "vertical": false, "font_size": 21, "lines_coords": [[[609.0, 888.0], [631.0, 888.0], [631.0, 909.0], [609.0, 909.0]]], "lines": ["や"]}, {"box": [363, 910, 409, 1005], "vertical": true, "font_size": 22, "lines_coords": [[[389.0, 911.0], [409.0, 911.0], [409.0, 1005.0], [389.0, 1005.0]], [[363.0, 910.0], [388.0, 910.0], [388.0, 973.0], [363.0, 973.0]]], "lines": ["やめとこう", "かな．．．"]}, {"box": [57, 1005, 89, 1038], "vertical": true, "font_size": 27, "lines_coords": [[[62.0, 1005.0], [89.0, 1010.0], [84.0, 1038.0], [57.0, 1033.0]]], "lines": ["あ"]}]}