{"version": "0.1.7", "img_width": 841, "img_height": 1200, "blocks": [{"box": [675, 522, 702, 582], "vertical": true, "font_size": 27, "lines_coords": [[[675.0, 522.0], [702.0, 522.0], [702.0, 582.0], [675.0, 582.0]]], "lines": ["いや．．．"]}, {"box": [508, 500, 594, 676], "vertical": true, "font_size": 19, "lines_coords": [[[565.0, 500.0], [585.0, 500.0], [585.0, 676.0], [565.0, 676.0]], [[536.0, 501.0], [556.0, 501.0], [556.0, 630.0], [536.0, 630.0]], [[509.0, 501.0], [525.0, 501.0], [525.0, 631.0], [509.0, 631.0]]], "lines": ["そこねお姉ちゃんの", "座るところなの", "降りてくれる？"]}, {"box": [436, 493, 477, 555], "vertical": true, "font_size": 41, "lines_coords": [[[436.0, 493.0], [477.0, 493.0], [477.0, 555.0], [436.0, 555.0]]], "lines": ["はっ"]}, {"box": [204, 491, 238, 555], "vertical": true, "font_size": 21, "lines_coords": [[[217.0, 491.0], [238.0, 491.0], [238.0, 536.0], [217.0, 536.0]]], "lines": ["こら"]}]}