{"version": "0.1.7", "img_width": 1078, "img_height": 1600, "blocks": [{"box": [860, 125, 945, 289], "vertical": true, "font_size": 22, "lines_coords": [[[918.0, 126.0], [940.0, 126.0], [940.0, 267.0], [918.0, 267.0]], [[892.0, 128.0], [913.0, 128.0], [913.0, 287.0], [892.0, 287.0]], [[860.0, 125.0], [882.0, 125.0], [884.0, 289.0], [862.0, 289.0]]], "lines": ["よーし気持ちを", "新たにするために", "席替えをするぞー"]}, {"box": [378, 114, 465, 367], "vertical": true, "font_size": 27, "lines_coords": [[[435.0, 114.0], [462.0, 114.0], [462.0, 290.0], [435.0, 290.0]], [[404.0, 115.0], [431.0, 115.0], [431.0, 367.0], [404.0, 367.0]], [[378.0, 115.0], [404.0, 115.0], [404.0, 357.0], [378.0, 357.0]]], "lines": ["今の席藤宮さんが", "結構近いし視界に入るしで", "嫌いじゃないんだけどなー"]}, {"box": [909, 492, 940, 620], "vertical": true, "font_size": 22, "lines_coords": [[[909.0, 492.0], [931.0, 492.0], [932.0, 620.0], [910.0, 620.0]]], "lines": ["席替えかー．．．"]}, {"box": [612, 501, 685, 664], "vertical": true, "font_size": 22, "lines_coords": [[[663.0, 504.0], [685.0, 504.0], [685.0, 623.0], [663.0, 623.0]], [[642.0, 501.0], [663.0, 501.0], [660.0, 604.0], [638.0, 604.0]], [[612.0, 504.0], [634.0, 504.0], [634.0, 664.0], [612.0, 664.0]]], "lines": ["先生偉いから", "すでにくじ", "作っておいたぞ！"]}, {"box": [542, 596, 592, 735], "vertical": true, "font_size": 22, "lines_coords": [[[570.0, 596.0], [592.0, 596.0], [592.0, 715.0], [570.0, 715.0]], [[542.0, 598.0], [562.0, 598.0], [562.0, 735.0], [542.0, 735.0]]], "lines": ["出席番号順に", "取りにこいよー"]}, {"box": [348, 473, 472, 735], "vertical": true, "font_size": 30, "lines_coords": [[[439.0, 473.0], [470.0, 473.0], [467.0, 671.0], [435.0, 671.0]], [[404.0, 475.0], [437.0, 473.0], [442.0, 615.0], [409.0, 617.0]], [[376.0, 475.0], [407.0, 475.0], [407.0, 735.0], [376.0, 735.0]], [[348.0, 475.0], [374.0, 475.0], [374.0, 693.0], [348.0, 693.0]]], "lines": ["もっと近くなったら", "嬉しい：けど", "もし俺より藤宮さんの方が", "後ろの席になったら？"]}, {"box": [152, 488, 190, 600], "vertical": true, "font_size": 38, "lines_coords": [[[152.0, 488.0], [190.0, 488.0], [190.0, 600.0], [152.0, 600.0]]], "lines": ["早くくじ引け"]}, {"box": [56, 478, 113, 669], "vertical": true, "font_size": 21, "lines_coords": [[[81.0, 479.0], [103.0, 479.0], [103.0, 612.0], [81.0, 612.0]], [[56.0, 478.0], [76.0, 478.0], [76.0, 665.0], [56.0, 665.0]]], "lines": ["全然見れなく", "なっちゃうんじゃ？"]}, {"box": [817, 884, 945, 1173], "vertical": true, "font_size": 52, "lines_coords": [[[878.0, 885.0], [940.0, 884.0], [945.0, 1026.0], [884.0, 1028.0]], [[820.0, 890.0], [862.0, 890.0], [862.0, 971.0], [820.0, 971.0]], [[817.0, 950.0], [860.0, 950.0], [860.0, 1173.0], [817.0, 1173.0]]], "lines": ["先生！", "．．．", "番後ろの"]}, {"box": [738, 882, 798, 1214], "vertical": true, "font_size": 52, "lines_coords": [[[738.0, 882.0], [798.0, 882.0], [798.0, 1214.0], [738.0, 1214.0]]], "lines": ["席がいいです！"]}, {"box": [93, 939, 254, 1379], "vertical": true, "font_size": 44, "lines_coords": [[[199.0, 939.0], [243.0, 939.0], [240.0, 1162.0], [196.0, 1162.0]], [[145.0, 940.0], [192.0, 940.0], [192.0, 1312.0], [145.0, 1312.0]], [[93.0, 940.0], [135.0, 940.0], [135.0, 1379.0], [93.0, 1379.0]]], "lines": ["ほぼ全員そう", "思ってるっていうのに", "よく室々と口に出せるな！"]}]}