{"version": "0.1.7", "img_width": 1352, "img_height": 1920, "blocks": [{"box": [1115, 1018, 1207, 1205], "vertical": true, "font_size": 30, "lines_coords": [[[1175.0, 1018.0], [1207.0, 1018.0], [1207.0, 1128.0], [1175.0, 1128.0]], [[1143.0, 1018.0], [1175.0, 1018.0], [1175.0, 1205.0], [1143.0, 1205.0]], [[1115.0, 1020.0], [1141.0, 1020.0], [1141.0, 1175.0], [1115.0, 1175.0]]], "lines": ["わかった", "きれいな言葉を", "使っていこう"]}, {"box": [721, 1153, 757, 1211], "vertical": true, "font_size": 36, "lines_coords": [[[721.0, 1153.0], [757.0, 1153.0], [757.0, 1211.0], [721.0, 1211.0]]], "lines": ["はい"]}, {"box": [144, 1008, 205, 1217], "vertical": true, "font_size": 25, "lines_coords": [[[178.0, 1010.0], [204.0, 1010.0], [204.0, 1117.0], [178.0, 1117.0]], [[144.0, 1008.0], [168.0, 1008.0], [168.0, 1216.0], [144.0, 1216.0]]], "lines": ["ご注文は", "お決まりですが？"]}, {"box": [568, 1454, 596, 1621], "vertical": true, "font_size": 26, "lines_coords": [[[568.0, 1455.0], [594.0, 1455.0], [594.0, 1620.0], [568.0, 1620.0]]], "lines": ["お決まりです"]}]}