{"version": "0.1.7", "img_width": 1352, "img_height": 1920, "blocks": [{"box": [1160, 148, 1214, 296], "vertical": true, "font_size": 24, "lines_coords": [[[1192.0, 150.0], [1213.0, 150.0], [1213.0, 271.0], [1192.0, 271.0]], [[1160.0, 148.0], [1186.0, 148.0], [1186.0, 296.0], [1160.0, 296.0]]], "lines": ["．．．なるほど", "道に迷ったと"]}, {"box": [734, 163, 825, 373], "vertical": true, "font_size": 24, "lines_coords": [[[796.0, 165.0], [823.0, 165.0], [823.0, 348.0], [796.0, 348.0]], [[763.0, 163.0], [789.0, 163.0], [791.0, 373.0], [765.0, 373.0]], [[735.0, 163.0], [755.0, 163.0], [755.0, 292.0], [735.0, 292.0]]], "lines": ["この辺りは特に", "あちゃめちゃして", "ますからね"]}, {"box": [571, 313, 628, 483], "vertical": true, "font_size": 26, "lines_coords": [[[603.0, 313.0], [628.0, 313.0], [628.0, 483.0], [603.0, 483.0]], [[571.0, 315.0], [598.0, 315.0], [598.0, 436.0], [571.0, 436.0]]], "lines": ["この子：小学生", "なのかな．．．"]}, {"box": [131, 268, 191, 491], "vertical": true, "font_size": 26, "lines_coords": [[[161.0, 270.0], [187.0, 270.0], [187.0, 491.0], [161.0, 491.0]], [[131.0, 268.0], [157.0, 268.0], [157.0, 369.0], [131.0, 369.0]]], "lines": ["なんかしっかりした", "子だな．．．"]}, {"box": [1125, 682, 1211, 913], "vertical": true, "font_size": 26, "lines_coords": [[[1183.0, 682.0], [1209.0, 682.0], [1209.0, 877.0], [1183.0, 877.0]], [[1153.0, 682.0], [1179.0, 682.0], [1179.0, 913.0], [1153.0, 913.0]], [[1125.0, 682.0], [1151.0, 682.0], [1151.0, 783.0], [1125.0, 783.0]]], "lines": ["駅の方まで行けば", "あとはわかりやすい", "ですから"]}, {"box": [772, 592, 828, 693], "vertical": true, "font_size": 26, "lines_coords": [[[796.0, 592.0], [828.0, 592.0], [828.0, 693.0], [796.0, 693.0]], [[772.0, 592.0], [793.0, 592.0], [793.0, 688.0], [772.0, 688.0]]], "lines": ["案内して", "あげます"]}, {"box": [720, 780, 770, 916], "vertical": true, "font_size": 23, "lines_coords": [[[744.0, 780.0], [770.0, 780.0], [770.0, 806.0], [744.0, 806.0]], [[720.0, 781.0], [740.0, 781.0], [740.0, 911.0], [720.0, 911.0]]], "lines": ["あ", "ありがとう．．"]}, {"box": [579, 740, 635, 926], "vertical": true, "font_size": 22, "lines_coords": [[[609.0, 740.0], [633.0, 740.0], [633.0, 926.0], [609.0, 926.0]], [[579.0, 744.0], [600.0, 744.0], [600.0, 871.0], [579.0, 871.0]]], "lines": ["あなた学生さん", "ですよね？"]}, {"box": [382, 577, 408, 673], "vertical": true, "font_size": 26, "lines_coords": [[[382.0, 577.0], [408.0, 577.0], [408.0, 673.0], [382.0, 673.0]]], "lines": ["あっはい"]}, {"box": [264, 549, 318, 722], "vertical": true, "font_size": 26, "lines_coords": [[[283.0, 549.0], [315.0, 549.0], [318.0, 701.0], [286.0, 701.0]], [[264.0, 618.0], [285.0, 618.0], [290.0, 716.0], [270.0, 718.0]]], "lines": ["学校休みじゃ", "ないでしょ"]}, {"box": [140, 575, 226, 772], "vertical": true, "font_size": 26, "lines_coords": [[[198.0, 575.0], [225.0, 575.0], [225.0, 699.0], [198.0, 699.0]], [[168.0, 577.0], [195.0, 577.0], [195.0, 701.0], [168.0, 701.0]], [[140.0, 579.0], [165.0, 579.0], [165.0, 772.0], [140.0, 772.0]]], "lines": ["だめですよ", "平日昼間に", "ぶらぶらしてちゃ"]}, {"box": [577, 1149, 633, 1333], "vertical": true, "font_size": 25, "lines_coords": [[[607.0, 1151.0], [631.0, 1151.0], [631.0, 1333.0], [607.0, 1333.0]], [[577.0, 1149.0], [603.0, 1149.0], [603.0, 1297.0], [577.0, 1297.0]]], "lines": ["あ生徒手帳とか", "持ってます？"]}, {"box": [146, 1008, 206, 1141], "vertical": true, "font_size": 26, "lines_coords": [[[174.0, 1008.0], [206.0, 1008.0], [202.0, 1141.0], [170.0, 1141.0]], [[146.0, 1014.0], [166.0, 1014.0], [166.0, 1141.0], [146.0, 1141.0]]], "lines": ["持ってない", "ですけど．．．"]}, {"box": [1042, 1530, 1068, 1653], "vertical": true, "font_size": 26, "lines_coords": [[[1042.0, 1530.0], [1068.0, 1530.0], [1068.0, 1653.0], [1042.0, 1653.0]]], "lines": ["こっちです"]}, {"box": [737, 1574, 793, 1754], "vertical": true, "font_size": 24, "lines_coords": [[[763.0, 1575.0], [793.0, 1575.0], [793.0, 1670.0], [763.0, 1670.0]], [[738.0, 1575.0], [757.0, 1575.0], [757.0, 1753.0], [738.0, 1753.0]]], "lines": ["ホントに", "めぢゃめちゃだ．．．"]}, {"box": [570, 1423, 630, 1666], "vertical": true, "font_size": 26, "lines_coords": [[[600.0, 1423.0], [626.0, 1423.0], [630.0, 1546.0], [603.0, 1546.0]], [[571.0, 1425.0], [598.0, 1425.0], [596.0, 1666.0], [570.0, 1666.0]]], "lines": ["もしかして", "おまわりさんですか？"]}, {"box": [196, 1440, 256, 1597], "vertical": true, "font_size": 26, "lines_coords": [[[228.0, 1440.0], [255.0, 1440.0], [255.0, 1595.0], [228.0, 1595.0]], [[196.0, 1440.0], [221.0, 1440.0], [221.0, 1597.0], [196.0, 1597.0]]], "lines": ["私が警察官に", "見えますか？"]}, {"box": [140, 1616, 166, 1764], "vertical": true, "font_size": 25, "lines_coords": [[[140.0, 1616.0], [165.0, 1616.0], [165.0, 1764.0], [140.0, 1764.0]]], "lines": ["見えないです"]}]}