{"version": "0.1.7", "img_width": 1091, "img_height": 1600, "blocks": [{"box": [901, 82, 962, 281], "vertical": true, "font_size": 25, "lines_coords": [[[937.0, 82.0], [961.0, 82.0], [959.0, 281.0], [936.0, 281.0]], [[901.0, 84.0], [928.0, 84.0], [928.0, 198.0], [901.0, 198.0]]], "lines": ["じゃあジュラルミン", "乗っけて？"]}, {"box": [792, 196, 820, 275], "vertical": true, "font_size": 28, "lines_coords": [[[792.0, 196.0], [820.0, 196.0], [820.0, 275.0], [792.0, 275.0]]], "lines": ["こお？"]}, {"box": [526, 257, 549, 358], "vertical": true, "font_size": 22, "lines_coords": [[[526.0, 259.0], [548.0, 259.0], [548.0, 357.0], [526.0, 357.0]]], "lines": ["そうそう"]}, {"box": [728, 585, 789, 681], "vertical": true, "font_size": 32, "lines_coords": [[[753.0, 585.0], [789.0, 585.0], [789.0, 642.0], [753.0, 642.0]], [[728.0, 589.0], [756.0, 589.0], [756.0, 681.0], [728.0, 681.0]]], "lines": ["ほら", "ぴったり"]}, {"box": [465, 599, 506, 783], "vertical": true, "font_size": 36, "lines_coords": [[[465.0, 601.0], [506.0, 601.0], [506.0, 662.0], [465.0, 662.0]], [[468.0, 735.0], [498.0, 735.0], [498.0, 781.0], [468.0, 781.0]]], "lines": ["おー", "！！"]}, {"box": [332, 598, 407, 801], "vertical": true, "font_size": 28, "lines_coords": [[[373.0, 600.0], [401.0, 600.0], [398.0, 800.0], [370.0, 800.0]], [[334.0, 598.0], [361.0, 598.0], [359.0, 801.0], [332.0, 801.0]]], "lines": ["ひっぱって一緒に", "お散歩もできるよ"]}, {"box": [906, 1133, 943, 1285], "vertical": true, "font_size": 33, "lines_coords": [[[909.0, 1139.0], [942.0, 1139.0], [939.0, 1285.0], [906.0, 1285.0]]], "lines": ["ころころ"]}]}