{"version": "0.1.7", "img_width": 980, "img_height": 1400, "blocks": [{"box": [194, 13, 225, 28], "vertical": false, "font_size": 15, "lines_coords": [[[194.0, 13.0], [225.0, 13.0], [225.0, 28.0], [194.0, 28.0]]], "lines": ["．．．"]}, {"box": [252, 15, 440, 28], "vertical": false, "font_size": 13, "lines_coords": [[[252.0, 15.0], [440.0, 15.0], [440.0, 28.0], [252.0, 28.0]]], "lines": ["人の捕みが分かるほど"]}, {"box": [479, 373, 490, 397], "vertical": true, "font_size": 11, "lines_coords": [[[479.0, 373.0], [490.0, 373.0], [490.0, 397.0], [479.0, 397.0]]], "lines": ["こそ"]}, {"box": [393, 54, 625, 1337], "vertical": true, "font_size": 45.4, "lines_coords": [[[593.0, 72.0], [625.0, 72.0], [624.0, 1327.0], [591.0, 1327.0]], [[548.0, 75.0], [575.0, 75.0], [571.0, 1328.0], [543.0, 1328.0]], [[496.0, 71.0], [533.0, 71.0], [523.0, 1304.0], [486.0, 1304.0]], [[399.0, 56.0], [496.0, 54.0], [522.0, 1320.0], [425.0, 1322.0]], [[396.0, 73.0], [429.0, 73.0], [426.0, 1337.0], [393.0, 1337.0]]], "lines": ["ないわ！」と捨て思いを残して、出て行ってしまった。僕はボーゼンと取り残されて突っ立つ", "ていた．．．。とんでもない笑い話さ。お互いの心の内をストレＩトに伝え合うことができたか", "ち、もう取り返しのつかないほど仲が悪くなってしまった。でも僕らは笑い話ですんでまだ", "なんだか．．．間宮、ちゅうちゅくちゅっと俺達出させてるんだろうからなんて言ってるのかなぁ。", "のきわに思っていることが、あわてて駆けつけた人達に伝わって、彼らを発狂させてしまった。"]}, {"box": [151, 71, 375, 1333], "vertical": true, "font_size": 32.0, "lines_coords": [[[347.0, 72.0], [375.0, 72.0], [374.0, 1330.0], [345.0, 1330.0]], [[297.0, 71.0], [330.0, 71.0], [326.0, 1330.0], [293.0, 1330.0]], [[247.0, 72.0], [280.0, 72.0], [277.0, 1333.0], [244.0, 1333.0]], [[198.0, 72.0], [235.0, 72.0], [228.0, 1333.0], [191.0, 1333.0]], [[151.0, 75.0], [180.0, 75.0], [180.0, 298.0], [151.0, 298.0]]], "lines": ["別のところでは、今まで手を組みんでいた二人の政治家が、じつは互いに相手をいつか裏切って", "やろうと思っていたのがばれて、議会で殺し合いを始めた。決着がつかないで、そしてお互い", "に痛くなって止めたけどね。学校では、みんなが答えを教え合うこのでテストが成り立たなくな", "っていた。ああ、そういえば若い女性に近づいただけで、婦女塞行末逐と猥褻物陳列で訴えら", "れた奴もいたな」"]}, {"box": [628, 62, 732, 1343], "vertical": true, "font_size": 44.0, "lines_coords": [[[687.0, 72.0], [732.0, 72.0], [732.0, 1335.0], [687.0, 1335.0]], [[675.0, 877.0], [688.0, 877.0], [688.0, 933.0], [675.0, 933.0]], [[628.0, 62.0], [702.0, 62.0], [702.0, 1343.0], [628.0, 1343.0]]], "lines": ["いていなかったのさ．．．！？私、彼女が僕はそれをとに気づいてるんだろうと思ってることも、気が", "おいけ", "いーーーっとづいてなかった。彼女は、「あんたみたいなさ」オレといった写真人間と、一緒になるでいられ"]}, {"box": [739, 73, 921, 1328], "vertical": true, "font_size": 32.75, "lines_coords": [[[889.0, 73.0], [921.0, 73.0], [918.0, 1223.0], [887.0, 1223.0]], [[840.0, 99.0], [873.0, 99.0], [870.0, 1248.0], [837.0, 1248.0]], [[791.0, 86.0], [824.0, 86.0], [821.0, 1328.0], [788.0, 1328.0]], [[739.0, 76.0], [772.0, 76.0], [772.0, 1327.0], [739.0, 1327.0]]], "lines": ["っても重要なことが、やっぱりあなたにとってはそんなことなのね！」「そう返事が来た」", "男の顔に、今度はほんの少し笑みが浮かんだ。それは、自嘲するような笑い方だった。", "「その後は、ひたすらテレパシ１でケンカさ。実はね、彼女は僕に対して、学歴面、そして頭", "脳面での劣等感を常に持っていたんだ。僕は長年つき合っていて、そのことにまったく気がつ"]}, {"box": [229, 1059, 240, 1086], "vertical": true, "font_size": 11, "lines_coords": [[[229.0, 1059.0], [240.0, 1059.0], [240.0, 1086.0], [229.0, 1086.0]]], "lines": ["オレ"]}, {"box": [225, 1116, 240, 1183], "vertical": true, "font_size": 15, "lines_coords": [[[225.0, 1116.0], [240.0, 1116.0], [240.0, 1183.0], [225.0, 1183.0]]], "lines": ["ぷっちん"]}, {"box": [445, 1301, 522, 1330], "vertical": false, "font_size": 29, "lines_coords": [[[445.0, 1301.0], [522.0, 1301.0], [522.0, 1330.0], [445.0, 1330.0]]], "lines": ["際ぁよ"]}]}