{"version": "0.1.7", "img_width": 980, "img_height": 1400, "blocks": [{"box": [98, 16, 366, 34], "vertical": false, "font_size": 18, "lines_coords": [[[98.0, 16.0], [366.0, 16.0], [366.0, 34.0], [98.0, 34.0]]], "lines": ["１１９第四話「コロンアム」"]}, {"box": [419, 109, 440, 149], "vertical": false, "font_size": 40, "lines_coords": [[[419.0, 109.0], [440.0, 109.0], [440.0, 149.0], [419.0, 149.0]]], "lines": ["うっぱ"]}, {"box": [371, 173, 386, 233], "vertical": true, "font_size": 15, "lines_coords": [[[371.0, 173.0], [386.0, 173.0], [386.0, 233.0], [371.0, 233.0]]], "lines": ["ゆんかん"]}, {"box": [438, 75, 584, 533], "vertical": true, "font_size": 28.0, "lines_coords": [[[569.0, 311.0], [584.0, 311.0], [584.0, 343.0], [569.0, 343.0]], [[537.0, 75.0], [574.0, 75.0], [574.0, 470.0], [537.0, 470.0]], [[489.0, 106.0], [520.0, 106.0], [520.0, 533.0], [489.0, 533.0]], [[442.0, 106.0], [471.0, 106.0], [467.0, 345.0], [438.0, 345.0]]], "lines": ["にら", "だけ上げてキノを睨みつけた。", "キノは『カノン』を右手で叩く。", "ぷわゎわわわーん"]}, {"box": [766, 108, 783, 166], "vertical": false, "font_size": 28.0, "lines_coords": [[[766.0, 108.0], [783.0, 108.0], [783.0, 136.0], [766.0, 136.0]], [[766.0, 138.0], [783.0, 138.0], [783.0, 166.0], [766.0, 166.0]]], "lines": ["こう", "さん"]}, {"box": [522, 462, 533, 490], "vertical": true, "font_size": 11, "lines_coords": [[[522.0, 462.0], [533.0, 462.0], [533.0, 490.0], [522.0, 490.0]]], "lines": ["大丈"]}, {"box": [97, 76, 420, 1328], "vertical": true, "font_size": 29.857142857142858, "lines_coords": [[[389.0, 108.0], [418.0, 108.0], [420.0, 325.0], [392.0, 325.0]], [[340.0, 105.0], [373.0, 105.0], [374.0, 1323.0], [341.0, 1323.0]], [[291.0, 76.0], [323.0, 76.0], [325.0, 894.0], [292.0, 894.0]], [[243.0, 103.0], [271.0, 103.0], [273.0, 1326.0], [244.0, 1326.0]], [[192.0, 79.0], [225.0, 79.0], [225.0, 1328.0], [192.0, 1328.0]], [[146.0, 80.0], [174.0, 80.0], [174.0, 326.0], [146.0, 326.0]], [[97.0, 109.0], [124.0, 109.0], [124.0, 1327.0], [97.0, 1327.0]]], "lines": ["喇叭音が響いた。", "その瞬間、男は右手で腹の鉄片をつかみ取ると、キノめがけて投げた。すぐ腹に手を返し、", "続けざまに投げつける。手が見ええないほどのスピードだった。", "キノは右側に走りながらよけた。すぐ脇を鉄片が回転しながらあら、猛烈なスピードで飛び去っ", "ていく。男は投げ続け、今度はキャノの右側を狙って投げた。キノは左側にステップを踏みながら、", "ら、全てをよけた。", "男は全部投げず、半分ほどが腹部にくっついたままだった。腰を前後に振りながら、怪しい"]}, {"box": [586, 76, 914, 1330], "vertical": true, "font_size": 28.428571428571427, "lines_coords": [[[887.0, 92.0], [914.0, 92.0], [914.0, 1041.0], [887.0, 1041.0]], [[836.0, 105.0], [865.0, 105.0], [865.0, 438.0], [836.0, 438.0]], [[785.0, 103.0], [817.0, 103.0], [817.0, 467.0], [785.0, 467.0]], [[736.0, 102.0], [765.0, 102.0], [768.0, 505.0], [739.0, 505.0]], [[690.0, 90.0], [717.0, 90.0], [717.0, 1327.0], [690.0, 1327.0]], [[641.0, 76.0], [665.0, 76.0], [668.0, 475.0], [643.0, 475.0]], [[586.0, 105.0], [617.0, 105.0], [621.0, 1330.0], [590.0, 1330.0]]], "lines": ["「うひゅひゅ。見たがあ？俺の手製手裏剣は、全て元に戻ってくるう", "キノは軽く顔をしかめた。", "それからおもむろに言った。", "降参してください。認めます。", "「それはあ、イヤだねえ。きみこそ降参したらあ？まあ、死ぬまあでぇ認めてあげないけれ", "どねえ。うひゅひゅひゃひゅっ", "男が笑いながら答えた。両手でお腹を押さえる仕草をする。そして少し前屈みになって、首を"]}, {"box": [127, 1237, 142, 1271], "vertical": true, "font_size": 15, "lines_coords": [[[127.0, 1237.0], [142.0, 1237.0], [142.0, 1271.0], [127.0, 1271.0]]], "lines": ["あや"]}, {"box": [617, 1066, 636, 1122], "vertical": true, "font_size": 19, "lines_coords": [[[617.0, 1066.0], [636.0, 1066.0], [636.0, 1122.0], [617.0, 1122.0]]], "lines": ["まえかが"]}]}