{"version": "0.1.7", "img_width": 980, "img_height": 1400, "blocks": [{"box": [95, 24, 427, 47], "vertical": false, "font_size": 23, "lines_coords": [[[95.0, 24.0], [427.0, 24.0], [427.0, 47.0], [95.0, 47.0]]], "lines": ["２３３．エピローグ「森の中で・ａ」"]}, {"box": [727, 123, 826, 612], "vertical": true, "font_size": 35, "lines_coords": [[[783.0, 123.0], [820.0, 123.0], [820.0, 596.0], [783.0, 596.0]], [[729.0, 147.0], [762.0, 147.0], [759.0, 523.0], [727.0, 523.0]]], "lines": ["エピローグ「森の中で・ａ", "Ｌｉｃｈｉｎｅｔｏｎｇｒａｌ"]}, {"box": [95, 86, 615, 1346], "vertical": true, "font_size": 30.272727272727273, "lines_coords": [[[591.0, 123.0], [615.0, 123.0], [615.0, 272.0], [591.0, 272.0]], [[539.0, 118.0], [567.0, 118.0], [567.0, 1341.0], [539.0, 1341.0]], [[489.0, 90.0], [522.0, 90.0], [522.0, 427.0], [489.0, 427.0]], [[440.0, 120.0], [471.0, 120.0], [471.0, 1043.0], [440.0, 1043.0]], [[389.0, 118.0], [420.0, 118.0], [420.0, 1345.0], [389.0, 1345.0]], [[334.0, 86.0], [371.0, 86.0], [374.0, 1346.0], [337.0, 1346.0]], [[291.0, 91.0], [322.0, 91.0], [322.0, 1289.0], [291.0, 1289.0]], [[241.0, 102.0], [273.0, 102.0], [273.0, 519.0], [241.0, 519.0]], [[192.0, 124.0], [221.0, 124.0], [221.0, 456.0], [192.0, 456.0]], [[144.0, 118.0], [173.0, 118.0], [172.0, 375.0], [143.0, 375.0]], [[97.0, 121.0], [124.0, 121.0], [123.0, 479.0], [95.0, 479.0]]], "lines": ["森の夜の中、", "そこには太い木々が立ち並び、彼らの枝と葉はまるで天義になっていた。昼間なら鮮やかな", "緑の葉も、今は黒かった。", "地面に広がる根のそばで、たき火、に残った小さな炎が揺らめいていた。", "その炎が作る薄暗闇の中、キャラノはコートにくるまるように体をを丸めて、太い幹と根が作るな", "だらかな由線に寄りかかって目を閉じていた。たき火から少しし離れたところには、荷物を全て", "おろしたエルメスが止まっている。メッキのパーツに、小さな炎がちらちらと映っていた。", "「キノ？まだ起きてるかい？」", "エルメスが小声で聞いた。", "ああ。起きてるよ」", "キノはすぐに返事を返した"]}, {"box": [470, 771, 483, 817], "vertical": true, "font_size": 13, "lines_coords": [[[470.0, 771.0], [483.0, 771.0], [483.0, 817.0], [470.0, 817.0]]], "lines": ["ほのお"]}]}