{"version": "0.1.7", "img_width": 1481, "img_height": 2142, "blocks": [{"box": [1345, 190, 1418, 360], "vertical": true, "font_size": 67, "lines_coords": [[[1351.0, 190.0], [1418.0, 192.0], [1411.0, 359.0], [1345.0, 357.0]]], "lines": ["よーし"]}, {"box": [294, 119, 468, 453], "vertical": true, "font_size": 52, "lines_coords": [[[414.0, 121.0], [466.0, 121.0], [466.0, 320.0], [414.0, 320.0]], [[355.0, 121.0], [407.0, 121.0], [403.0, 363.0], [351.0, 363.0]], [[294.0, 119.0], [345.0, 119.0], [345.0, 453.0], [294.0, 453.0]]], "lines": ["きょうは", "はりきって", "がんばるぞー！"]}, {"box": [1286, 696, 1330, 853], "vertical": true, "font_size": 44, "lines_coords": [[[1286.0, 696.0], [1330.0, 696.0], [1330.0, 853.0], [1286.0, 853.0]]], "lines": ["よつばー"]}, {"box": [1368, 1075, 1414, 1242], "vertical": true, "font_size": 46, "lines_coords": [[[1368.0, 1075.0], [1414.0, 1075.0], [1414.0, 1177.0], [1368.0, 1177.0]]], "lines": ["ういー"]}, {"box": [700, 1031, 835, 1267], "vertical": true, "font_size": 34, "lines_coords": [[[801.0, 1039.0], [830.0, 1039.0], [830.0, 1265.0], [801.0, 1265.0]], [[759.0, 1039.0], [788.0, 1039.0], [788.0, 1267.0], [759.0, 1267.0]], [[700.0, 1031.0], [744.0, 1031.0], [744.0, 1144.0], [700.0, 1144.0]]], "lines": ["よつばちゃんも", "みうらちゃんち", "行く？"]}, {"box": [232, 1060, 320, 1345], "vertical": true, "font_size": 35, "lines_coords": [[[278.0, 1060.0], [313.0, 1060.0], [313.0, 1345.0], [278.0, 1345.0]], [[234.0, 1060.0], [269.0, 1060.0], [267.0, 1309.0], [232.0, 1309.0]]], "lines": ["よつばはいまから", "おでかけなので"]}, {"box": [1240, 1692, 1343, 1926], "vertical": true, "font_size": 36, "lines_coords": [[[1301.0, 1696.0], [1338.0, 1696.0], [1338.0, 1886.0], [1301.0, 1886.0]], [[1242.0, 1692.0], [1278.0, 1692.0], [1278.0, 1924.0], [1242.0, 1924.0]]], "lines": ["おでかけ？", "どこ行くの？"]}]}