{"version": "0.1.7", "img_width": 1479, "img_height": 2129, "blocks": [{"box": [1183, 145, 1315, 465], "vertical": true, "font_size": 33, "lines_coords": [[[1277.0, 145.0], [1312.0, 145.0], [1312.0, 465.0], [1277.0, 465.0]], [[1233.0, 147.0], [1262.0, 147.0], [1262.0, 430.0], [1233.0, 430.0]], [[1183.0, 147.0], [1218.0, 147.0], [1218.0, 361.0], [1183.0, 361.0]]], "lines": ["いじめられたのか？", "ふーかにわるくち", "いわれたか？"]}, {"box": [374, 128, 515, 401], "vertical": true, "font_size": 36, "lines_coords": [[[476.0, 128.0], [511.0, 128.0], [511.0, 401.0], [476.0, 401.0]], [[424.0, 128.0], [461.0, 128.0], [461.0, 286.0], [424.0, 286.0]], [[374.0, 130.0], [411.0, 130.0], [411.0, 322.0], [374.0, 322.0]]], "lines": ["なんかあったら", "よつばに", "いいなよ？"]}, {"box": [104, 145, 158, 241], "vertical": true, "font_size": 54, "lines_coords": [[[104.0, 145.0], [158.0, 145.0], [158.0, 241.0], [104.0, 241.0]]], "lines": ["うん"]}, {"box": [774, 532, 877, 732], "vertical": true, "font_size": 49, "lines_coords": [[[809.0, 532.0], [877.0, 532.0], [877.0, 619.0], [809.0, 619.0]], [[775.0, 540.0], [805.0, 540.0], [805.0, 731.0], [775.0, 731.0]]], "lines": ["悪口", "言われてない"]}, {"box": [859, 1143, 1023, 1496], "vertical": true, "font_size": 50, "lines_coords": [[[973.0, 1145.0], [1023.0, 1145.0], [1023.0, 1411.0], [973.0, 1411.0]], [[919.0, 1143.0], [969.0, 1143.0], [965.0, 1496.0], [915.0, 1496.0]], [[863.0, 1143.0], [913.0, 1143.0], [909.0, 1413.0], [859.0, 1413.0]]], "lines": ["とーちゃんは", "よつばがまもって", "やるからな！"]}, {"box": [220, 1230, 260, 1316], "vertical": true, "font_size": 40, "lines_coords": [[[220.0, 1230.0], [260.0, 1230.0], [260.0, 1316.0], [220.0, 1316.0]]], "lines": ["うん"]}]}