{"version": "0.1.7", "img_width": 1485, "img_height": 2137, "blocks": [{"box": [1274, 146, 1311, 439], "vertical": true, "font_size": 27, "lines_coords": [[[1276.0, 146.0], [1303.0, 146.0], [1303.0, 436.0], [1276.0, 436.0]]], "lines": ["これはいるかちがう"]}, {"box": [707, 171, 782, 431], "vertical": true, "font_size": 32, "lines_coords": [[[744.0, 171.0], [780.0, 171.0], [782.0, 429.0], [746.0, 429.0]], [[707.0, 173.0], [736.0, 173.0], [736.0, 431.0], [707.0, 431.0]]], "lines": ["いるかのしっぽは", "たてとちがうので"]}, {"box": [606, 258, 636, 479], "vertical": true, "font_size": 32, "lines_coords": [[[606.0, 258.0], [636.0, 258.0], [636.0, 479.0], [606.0, 479.0]]], "lines": ["いるかはいない"]}, {"box": [429, 142, 483, 287], "vertical": true, "font_size": 54, "lines_coords": [[[429.0, 146.0], [483.0, 146.0], [483.0, 287.0], [429.0, 287.0]]], "lines": ["０とう"]}, {"box": [477, 749, 577, 903], "vertical": true, "font_size": 100, "lines_coords": [[[477.0, 749.0], [577.0, 749.0], [577.0, 903.0], [477.0, 903.0]]], "lines": ["正解"]}, {"box": [1222, 1310, 1305, 1594], "vertical": true, "font_size": 35, "lines_coords": [[[1270.0, 1310.0], [1305.0, 1310.0], [1305.0, 1594.0], [1270.0, 1594.0]], [[1222.0, 1310.0], [1259.0, 1310.0], [1259.0, 1452.0], [1222.0, 1452.0]]], "lines": ["よく気づいたね！", "えらい！"]}, {"box": [1036, 1325, 1126, 1504], "vertical": true, "font_size": 35, "lines_coords": [[[1088.0, 1325.0], [1126.0, 1325.0], [1126.0, 1467.0], [1088.0, 1467.0]], [[1036.0, 1325.0], [1065.0, 1325.0], [1065.0, 1504.0], [1036.0, 1504.0]]], "lines": ["ひっかけ", "問題だよ！"]}, {"box": [807, 1335, 863, 1519], "vertical": true, "font_size": 35, "lines_coords": [[[807.0, 1335.0], [842.0, 1335.0], [842.0, 1519.0], [807.0, 1519.0]]], "lines": ["悪質だな！"]}, {"box": [625, 1383, 678, 1619], "vertical": true, "font_size": 50, "lines_coords": [[[625.0, 1383.0], [675.0, 1383.0], [675.0, 1619.0], [625.0, 1619.0]]], "lines": ["やったー！"]}, {"box": [450, 1070, 523, 1149], "vertical": true, "font_size": 73, "lines_coords": [[[450.0, 1070.0], [523.0, 1070.0], [523.0, 1149.0], [450.0, 1149.0]]], "lines": ["え"]}, {"box": [352, 1329, 489, 1652], "vertical": true, "font_size": 35, "lines_coords": [[[444.0, 1333.0], [479.0, 1333.0], [479.0, 1542.0], [444.0, 1542.0]], [[398.0, 1329.0], [433.0, 1329.0], [433.0, 1652.0], [398.0, 1652.0]], [[352.0, 1333.0], [387.0, 1333.0], [387.0, 1598.0], [352.0, 1598.0]]], "lines": ["じゃあその下の", "こたえって書いてる所に", "「０とう」って書いて"]}, {"box": [120, 1348, 158, 1446], "vertical": true, "font_size": 38, "lines_coords": [[[120.0, 1348.0], [158.0, 1348.0], [158.0, 1446.0], [120.0, 1446.0]]], "lines": ["ここ？"]}]}